README.rst
setup.py
pyGeoTile.egg-info/PKG-INFO
pyGeoTile.egg-info/SOURCES.txt
pyGeoTile.egg-info/dependency_links.txt
pyGeoTile.egg-info/top_level.txt
pygeotile/__init__.py
pygeotile/meta.py
pygeotile/point.py
pygeotile/tile.py