Metadata-Version: 1.0
Name: pyGeoTile
Version: 1.0.3
Summary: Python package to handle tiles and points of different projections, in particular WGS 84 (Latitude, Longitude), Spherical Mercator (Meters), Pixel Pyramid and Tiles (TMS, Google, QuadTree)
Home-page: https://github.com/geometalab/pyGeoTile
Author: Samuel Kurath
Author-email: geometalab@hsr.ch
License: MIT
Platform: UNKNOWN
